<annotation verified="yes">
	<folder>train</folder>
	<filename>Silent-Falcon-UAS.jpg</filename>
	<path>D:/images/train/Silent-Falcon-UAS.jpg</path>
	<source>
		<database>Unknown</database>
	</source>
	<size>
		<width>740</width>
		<height>576</height>
		<depth>3</depth>
	</size>
	<segmented>0</segmented>
	<object>
		<name>plane</name>
		<pose>Unspecified</pose>
		<truncated>0</truncated>
		<difficult>0</difficult>
		<bndbox>
			<xmin>17</xmin>
			<ymin>133</ymin>
			<xmax>669</xmax>
			<ymax>544</ymax>
		</bndbox>
	</object>
</annotation>
